setup.py
html2hamlpy/__init__.py
html2hamlpy/html.py
html2hamlpy.egg-info/PKG-INFO
html2hamlpy.egg-info/SOURCES.txt
html2hamlpy.egg-info/dependency_links.txt
html2hamlpy.egg-info/requires.txt
html2hamlpy.egg-info/top_level.txt