Metadata-Version: 1.0
Name: html2hamlpy
Version: 0.11.3
Summary: Convert Django-flavored HTML to HamlPy
Home-page: http://github.com/davidtingsu/html2hamlpy
Author: David Su
Author-email: dtscraft@gmail.com
License: MIT
Keywords: haml hamlpy django converter html2hamlpy
Platform: UNKNOWN
